mizutsune_taobaosearch_mcp_server/__init__.py
mizutsune_taobaosearch_mcp_server-0.1.3.dist-info/WHEEL
mizutsune_taobaosearch_mcp_server-0.1.3.dist-info/entry_points.txt
mizutsune_taobaosearch_mcp_server-0.1.3.dist-info/METADATA
mizutsune_taobaosearch_mcp_server-0.1.3.dist-info/RECORD
