Metadata-Version: 2.3
Name: mizutsune-taobaosearch-mcp-server
Version: 0.1.3
Summary: 这是一个淘宝的自动搜索并筛选价格区间的mcp-server，用户可以输入想要搜索的物品，并指定价格范围，让其返回n个商品的链接和图片以及分析。本意是做一个自动搜索电脑整机并且返回对比分析配置和价格，得出性价比的mcp，但是由于拿到url之后，每个淘宝店电脑配置的位置完全不一样，就退化为搜索商品并返回了，作为练手，不算很好用
Author: Mizutsune
Author-email: Mizutsune <872595975@qq.com>
Requires-Dist: asyncio>=4.0.0
Requires-Dist: fastmcp>=2.14.1
Requires-Dist: mcp[cli]>=1.25.0
Requires-Dist: playwright>=1.57.0
Requires-Dist: uuid>=1.30
Requires-Python: >=3.13
